LICENSE
MANIFEST.in
README.md
pip-requirements-test.txt
pip-requirements.txt
setup.py
weka/__init__.py
weka/arff.py
weka/classifiers.py
weka/tests.py
weka.egg-info/PKG-INFO
weka.egg-info/SOURCES.txt
weka.egg-info/dependency_links.txt
weka.egg-info/requires.txt
weka.egg-info/top_level.txt
weka/fixtures/.gitignore
weka/fixtures/abalone-query-bad.arff
weka/fixtures/abalone-query.arff
weka/fixtures/abalone-train.arff
weka/fixtures/abalone.arff
weka/fixtures/updateable-train-1.arff
weka/fixtures/updateable-train-2.arff