Metadata-Version: 2.1
Name: weka
Version: 2.0.1
Summary: A Python wrapper for the Weka data mining library.
Home-page: https://gitlab.com/chrisspen/weka
Author: Chris Spencer
Author-email: chrisspen@gmail.com
License: LGPL License
Platform: OS Independent
Classifier: Programming Language :: Python
Classifier: Programming Language :: Python :: 3.9
Classifier: Development Status :: 5 - Production/Stable
Classifier: License :: OSI Approved :: GNU Library or Lesser General Public License (LGPL)
Classifier: Operating System :: OS Independent
Classifier: Topic :: Software Development :: Libraries :: Python Modules
Classifier: Topic :: Text Processing :: General
License-File: LICENSE
